assuming.py
assuming-0.0.2.dist-info/LICENSE
assuming-0.0.2.dist-info/WHEEL
assuming-0.0.2.dist-info/METADATA
assuming-0.0.2.dist-info/RECORD
